jh_toolbox/__init__.py
jh_toolbox/embedding_function.py
jh_toolbox/data/config.json
jh_toolbox/data/model.onnx
jh_toolbox/data/special_tokens_map.json
jh_toolbox/data/tokenizer.json
jh_toolbox/data/tokenizer_config.json
jh_toolbox/data/vocab.txt
jh_toolbox-0.0.1.dist-info/METADATA
jh_toolbox-0.0.1.dist-info/WHEEL
jh_toolbox-0.0.1.dist-info/licenses/LICENSE
jh_toolbox-0.0.1.dist-info/RECORD
