Metadata-Version: 2.4
Name: jh-toolbox
Version: 0.0.1
Summary: JH's python toolbox
Author-email: JH <author@example.com>
License-Expression: MIT
License-File: LICENSE
Classifier: Operating System :: OS Independent
Classifier: Programming Language :: Python :: 3
Requires-Python: >=3.9
